Metadata-Version: 2.1
Name: clrfterm
Version: 1.0.4
Summary: Module that decorates your console
Home-page: https://github.com/SayHelloRoman/clrfterm
License: UNKNOWN
Platform: UNKNOWN
License-File: LICENSE
